{"is_source_file": true, "format": "Python (Django migration script)", "description": "This file is a Django migration script generated by the Kavia Code Generation Agent. It defines database schema migrations for creating models related to a food ordering system, including Customer, Category, MenuItem, Order, OrderItem, Payment, and OrderStatusEvent. The script specifies the fields, indexes, constraints, and dependencies for these models to set up the initial database schema.", "external_files": ["django.db", "django.core.validators", "django.utils.timezone"], "external_methods": ["migrations.CreateModel", "models.BigAutoField", "models.DateTimeField", "models.BooleanField", "models.EmailField", "models.CharField", "models.TextField", "models.PositiveIntegerField", "models.URLField", "models.ForeignKey", "models.OneToOneField", "migrations.AddIndex", "migrations.AddConstraint"], "published": [], "classes": [{"name": "Migration", "description": "A Django Migration class defining initial database schema for the food order backend."}], "methods": [{"name": "__init__", "description": "Initializes the Migration object; standard Django migration constructor."}], "calls": ["migrations.CreateModel", "migrations.AddIndex", "migrations.AddConstraint"], "search-terms": ["django migrations", "food order schema", "initial migration", "OrderStatusEvent", "MenuItem constraints", "Payment model", "Customer model"], "state": 2, "file_id": 19, "knowledge_revision": 41, "git_revision": "", "ctags": [{"_type": "tag", "name": "Migration", "path": "/home/kavia/workspace/code-generation/food-order-tracker-22822-22831/food_order_backend/api/migrations/0001_initial.py", "pattern": "/^class Migration(migrations.Migration):$/", "language": "Python", "kind": "class"}, {"_type": "tag", "name": "dependencies", "path": "/home/kavia/workspace/code-generation/food-order-tracker-22822-22831/food_order_backend/api/migrations/0001_initial.py", "pattern": "/^    dependencies = [$/", "language": "Python", "kind": "variable", "scope": "Migration", "scopeKind": "class"}, {"_type": "tag", "name": "initial", "path": "/home/kavia/workspace/code-generation/food-order-tracker-22822-22831/food_order_backend/api/migrations/0001_initial.py", "pattern": "/^    initial = True$/", "language": "Python", "kind": "variable", "scope": "Migration", "scopeKind": "class"}, {"_type": "tag", "name": "operations", "path": "/home/kavia/workspace/code-generation/food-order-tracker-22822-22831/food_order_backend/api/migrations/0001_initial.py", "pattern": "/^    operations = [$/", "language": "Python", "kind": "variable", "scope": "Migration", "scopeKind": "class"}], "hash": "674ab9c85e9efe00d88ee67f2b5aae2c", "format-version": 4, "code-base-name": "food_order_backend", "filename": "food_order_backend/api/migrations/0001_initial.py", "fields": [{"name": "dependencies = [", "scope": "Migration", "scopeKind": "class", "description": "unavailable"}, {"name": "initial = True", "scope": "Migration", "scopeKind": "class", "description": "unavailable"}, {"name": "operations = [", "scope": "Migration", "scopeKind": "class", "description": "unavailable"}], "revision_history": [{"41": ""}]}